flask_nav3/__init__.py
flask_nav3/elements.py
flask_nav3/renderers.py
flask_nav3-0.7.2.dist-info/LICENSE
flask_nav3-0.7.2.dist-info/METADATA
flask_nav3-0.7.2.dist-info/WHEEL
flask_nav3-0.7.2.dist-info/RECORD
