Metadata-Version: 2.1
Name: flask-nav3
Version: 0.7.2
Summary: Easily create navigation for Flask applications.
Home-page: https://github.com/wtfo-guru/flask-nav3
License: MIT
Author: Quien Sabe
Author-email: qs5779@mail.com
Requires-Python: >=3.8.1,<4.0
Classifier: License :: OSI Approved :: MIT License
Classifier: Programming Language :: Python :: 3
Classifier: Programming Language :: Python :: 3.9
Classifier: Programming Language :: Python :: 3.10
Classifier: Programming Language :: Python :: 3.11
Classifier: Programming Language :: Python :: 3.12
Classifier: Programming Language :: Python :: 3.8
Classifier: Typing :: Typed
Requires-Dist: dominate (>=2.9,<3.0)
Requires-Dist: flask (>=2.2.2,<4.0.0)
Requires-Dist: visitor (>=0.1.3,<0.2.0)
Project-URL: Documentation, https://flask-nav3.readthedocs.io/en/stable
